setup.py
aggregate/GlobalAggregateInfo.py
aggregate/__init__.py
aggregate/aggregate_to_json.py
aggregate/handler/AggregateObject.py
aggregate/handler/BaseHandler.py
aggregate/handler/ObjectAllocAndFreeHandler.py
aggregate/handler/ThreadContendHandler.py
aggregate/handler/ThreadStartHandler.py
aggregate/handler/__init__.py
event/Event.py
event/GCEvent.py
event/MonitorContendedEvent.py
event/ObjectAllocEvent.py
event/ObjectFreeEvent.py
event/StackEvent.py
event/ThreadStartEvent.py
event/__init__.py
handler/BaseHandler.py
handler/GCHandler.py
handler/MonitorContendedHandler.py
handler/ObjectAllocHandler.py
handler/ObjectFreeHandler.py
handler/ThreadStartHandler.py
handler/__init__.py
main/__init__.py
main/analyzer.py
plot/BaseMaker.py
plot/BokehPlotMaker.py
plot/MongoPlotMaker.py
plot/__init__.py
plot/maker/ObjectAllocLine.py
plot/maker/ObjectAllocPlot.py
plot/maker/ThreadContendPlot.py
plot/maker/ThreadContendSegment.py
plot/maker/__init__.py
tm_analyzer.egg-info/PKG-INFO
tm_analyzer.egg-info/SOURCES.txt
tm_analyzer.egg-info/dependency_links.txt
tm_analyzer.egg-info/entry_points.txt
tm_analyzer.egg-info/requires.txt
tm_analyzer.egg-info/top_level.txt
utils/ColorUtils.py
utils/ColorUtils_test.py
utils/JVMUtils.py
utils/JVMUtils_test.py
utils/__init__.py