Metadata-Version: 1.1
Name: tm-analyzer
Version: 0.0.1
Summary: A powerful tool to help Android engineers optimize their performance
Home-page: UNKNOWN
Author: zkwlx
Author-email: xuzhi@bytedance.com
License: UNKNOWN
Platform: UNKNOWN
Classifier: Programming Language :: Python :: 3 :: Only
